mathematical_expression/__init__.py
mathematical_expression/core/__init__.py
mathematical_expression/core/calculation/Calculation.py
mathematical_expression/core/calculation/SharedCalculation.py
mathematical_expression/core/calculation/__init__.py
mathematical_expression/core/calculation/bool/__init__.py
mathematical_expression/core/calculation/bool/booleanCalculation.py
mathematical_expression/core/calculation/bool/booleanCalculation2.py
mathematical_expression/core/calculation/function/ExpressionFunction.py
mathematical_expression/core/calculation/function/Function.py
mathematical_expression/core/calculation/function/__init__.py
mathematical_expression/core/calculation/number/__init__.py
mathematical_expression/core/calculation/number/bracketsCalculation.py
mathematical_expression/core/calculation/number/bracketsCalculation2.py
mathematical_expression/core/calculation/number/cumulativeCalculation.py
mathematical_expression/core/calculation/number/fastMultiplyOfIntervalsBrackets.py
mathematical_expression/core/calculation/number/fastSumOfIntervalsBrackets.py
mathematical_expression/core/calculation/number/functionFormulaCalculation.py
mathematical_expression/core/calculation/number/functionFormulaCalculation2.py
mathematical_expression/core/calculation/number/numberCalculation.py
mathematical_expression/core/calculation/number/prefixExpressionOperation.py
mathematical_expression/core/container/CalculationBooleanResults.py
mathematical_expression/core/container/CalculationNumberResults.py
mathematical_expression/core/container/CalculationResults.py
mathematical_expression/core/container/__init__.py
mathematical_expression/core/manager/CalculationManagement.py
mathematical_expression/core/manager/ConstantRegion.py
mathematical_expression/core/manager/__init__.py
mathematical_expression/exceptional/AbnormalOperation.py
mathematical_expression/exceptional/ExtractException.py
mathematical_expression/exceptional/UnsupportedOperationException.py
mathematical_expression_py-1.2.5.dist-info/LICENSE
mathematical_expression_py-1.2.5.dist-info/METADATA
mathematical_expression_py-1.2.5.dist-info/WHEEL
mathematical_expression_py-1.2.5.dist-info/top_level.txt
mathematical_expression_py-1.2.5.dist-info/RECORD
