Metadata-Version: 2.1
Name: mathematical-expression-py
Version: 1.2.5
Summary: Python API concise framework for parsing string mathematical expressions
Author-email: BeardedManZhao <liming7887@qq.com>
Project-URL: Homepage, https://github.com/BeardedManZhao/mathematical-expression-py
Project-URL: Bug Tracker, https://github.com/BeardedManZhao/mathematical-expression-py/issues
Classifier: Programming Language :: Python :: 3
Classifier: License :: OSI Approved :: Apache Software License
Classifier: Operating System :: OS Independent
Requires-Python: >=3.6
License-File: LICENSE
